daga/__init__.py
daga/functions.py
daga-0.0.4.dist-info/LICENSE
daga-0.0.4.dist-info/METADATA
daga-0.0.4.dist-info/WHEEL
daga-0.0.4.dist-info/top_level.txt
daga-0.0.4.dist-info/RECORD
