Metadata-Version: 2.1
Name: daga
Version: 0.0.4
Summary: This is a library that makes data augmentation based on SDV library using a single objective algorithm to get the distributions of the variables.
Author-email: Elene Astondoa and Ane Martínez <anemartinezorellana@outlook.es>
Project-URL: Homepage, https://github.com/anemartinez1/pypi_library
Project-URL: Bug Tracker, https://github.com/anemartinez1/pypi_library/issues
Classifier: Programming Language :: Python :: 3
Classifier: License :: OSI Approved :: MIT License
Classifier: Operating System :: OS Independent
Requires-Python: >=3.9
License-File: LICENSE
Provides-Extra: dev
Requires-Dist: pandas ; extra == 'dev'
Requires-Dist: cv2 ; extra == 'dev'
Requires-Dist: matplotlib.pyplot ; extra == 'dev'
Requires-Dist: sdv ; extra == 'dev'
Requires-Dist: sklearn ; extra == 'dev'
